datadog/__init__.py
datadog/apps.py
datadog/instrument.py
datadog/middleware.py
dbt_django_datadog-0.1.5.dist-info/METADATA
dbt_django_datadog-0.1.5.dist-info/WHEEL
dbt_django_datadog-0.1.5.dist-info/RECORD
