Metadata-Version: 2.3
Name: dbt-django-datadog
Version: 0.1.5
Summary: A package to configuring datadog for DBT applications running in DBT Platform (AWS copilot/fargate)
Author: sre@digital.trade.gov.uk
Requires-Python: >=3.11
Classifier: Programming Language :: Python :: 3
Classifier: Programming Language :: Python :: 3.11
Classifier: Programming Language :: Python :: 3.12
Classifier: Programming Language :: Python :: 3.13
Requires-Dist: ddtrace (>=3.12.5)
Requires-Dist: django (>=5.2.6,<6.0.0)
